radarexporterwebpage/__init__.py
radarexporterwebpage/load.py
radarexporterwebpage-1.0.12.dist-info/METADATA
radarexporterwebpage-1.0.12.dist-info/WHEEL
radarexporterwebpage-1.0.12.dist-info/top_level.txt
radarexporterwebpage-1.0.12.dist-info/RECORD
